odoo/addons/website_sale_secondary_unit/README.rst
odoo/addons/website_sale_secondary_unit/__init__.py
odoo/addons/website_sale_secondary_unit/__manifest__.py
odoo/addons/website_sale_secondary_unit/hooks.py
odoo/addons/website_sale_secondary_unit/controllers/__init__.py
odoo/addons/website_sale_secondary_unit/controllers/main.py
odoo/addons/website_sale_secondary_unit/data/demo.xml
odoo/addons/website_sale_secondary_unit/i18n/es.po
odoo/addons/website_sale_secondary_unit/i18n/website_sale_secondary_unit.pot
odoo/addons/website_sale_secondary_unit/models/__init__.py
odoo/addons/website_sale_secondary_unit/models/product_secondary_unit.py
odoo/addons/website_sale_secondary_unit/models/product_template.py
odoo/addons/website_sale_secondary_unit/models/sale_order.py
odoo/addons/website_sale_secondary_unit/readme/CONTRIBUTORS.rst
odoo/addons/website_sale_secondary_unit/readme/DESCRIPTION.rst
odoo/addons/website_sale_secondary_unit/readme/USAGE.rst
odoo/addons/website_sale_secondary_unit/security/ir.model.access.csv
odoo/addons/website_sale_secondary_unit/security/website_sale_secondary_unit.xml
odoo/addons/website_sale_secondary_unit/static/description/icon.png
odoo/addons/website_sale_secondary_unit/static/description/index.html
odoo/addons/website_sale_secondary_unit/static/src/js/website_sale_secondary_unit.js
odoo/addons/website_sale_secondary_unit/static/src/js/website_sale_secondary_unit_tour.js
odoo/addons/website_sale_secondary_unit/static/src/less/website_sale_secondary_unit.less
odoo/addons/website_sale_secondary_unit/tests/__init__.py
odoo/addons/website_sale_secondary_unit/tests/test_website_sale_secondary_unit.py
odoo/addons/website_sale_secondary_unit/views/assets.xml
odoo/addons/website_sale_secondary_unit/views/product_secondary_unit_views.xml
odoo/addons/website_sale_secondary_unit/views/product_template_views.xml
odoo/addons/website_sale_secondary_unit/views/templates.xml
odoo11_addon_website_sale_secondary_unit-11.0.1.0.0.99.dev7.dist-info/METADATA
odoo11_addon_website_sale_secondary_unit-11.0.1.0.0.99.dev7.dist-info/WHEEL
odoo11_addon_website_sale_secondary_unit-11.0.1.0.0.99.dev7.dist-info/top_level.txt
odoo11_addon_website_sale_secondary_unit-11.0.1.0.0.99.dev7.dist-info/RECORD
